# Java 程序计数器详解

## 什么是程序计数器？

程序计数器（Program Counter Register）是 Java 虚拟机（JVM）的一部分，用于记录线程正在执行的字节码指令的地址或偏移量。它是 JVM 内存模型中唯一一个线程私有的内存区域。

在 JVM 的运行时数据区域中，程序计数器是一个非常小但关键的组件，用于协调线程的执行，尤其是多线程之间的上下文切换。

## 程序计数器的功能

### 记录当前字节码指令的执行地址

当线程正在执行一个 Java 方法时，程序计数器会存储当前线程正在执行的字节码指令的地址（或偏移量）。这个地址指向方法区中的方法字节码。

### 支持线程切换

程序计数器是线程私有的，这意味着每个线程都有自己的独立程序计数器。

当多线程切换时，程序计数器会记录当前线程执行的位置，线程切换回来时，可以从记录的位置继续执行。

### 用于控制流程

程序计数器在 JVM 中负责控制流程指令，例如分支（if）、循环（for）、跳转（goto）、异常处理和方法调用返回等。通过修改程序计数器的值，JVM 可以跳转到不同的字节码指令执行。

### 特殊情况：本地方法

当线程正在执行本地方法（Native Method）时，程序计数器的值为 undefined，因为本地方法不依赖 JVM 的字节码指令，而是直接由操作系统或底层硬件执行。

# 程序计数器在 JVM 结构中的位置

JVM 的运行时数据区包括：

程序计数器（Program Counter Register，线程私有）
Java 虚拟机栈（JVM Stack，线程私有）
本地方法栈（Native Method Stack，线程私有）
堆（Heap，线程共享）
方法区（Method Area，线程共享）
直接内存（Direct Memory，线程共享）

程序计数器是其中最小的内存区域，其作用是为当前线程提供指令执行的控制。

# 程序计数器的特点

## 线程私有

每个线程都有自己独立的程序计数器，互不干扰。
在多线程环境中，程序计数器保证每个线程都能准确记录自己执行的位置，支持上下文切换。

## 固定大小

程序计数器的内存占用很小，因为它只需要记录一个地址或偏移量。

## 不可见性

程序计数器是 JVM 的底层实现细节，开发者无法直接操作或访问它。

## 功能简单但关键

它负责记录和管理线程执行的字节码指令位置，是 JVM 实现多线程的核心之一。

# 程序计数器的两种状态

## Java 方法执行时：记录字节码指令地址

对于 Java 方法，程序计数器记录当前正在执行的字节码指令的地址。
它会在方法调用、跳转或线程切换时更新，以保证执行的连续性。

## 本地方法执行时：Undefined

当线程执行本地方法时，程序计数器没有具体的值。
原因是本地方法不依赖 JVM 的字节码，而是直接调用底层系统或硬件，因此计数器的值无意义。

# 示例解析

```java

public class ProgramCounterExample {
    public static void main(String[] args) {
        int a = 5;
        int b = 10;
        int c = a + b;
        System.out.println("Sum: " + c);
    }
}
```

对应的字节码如下（使用 javap -c ProgramCounterExample 查看）：

kotlin

 0: iconst_5       // 将常量 5 压入操作数栈

 1: istore_1       // 将栈顶值存入局部变量表索引 1

 2: iconst_10      // 将常量 10 压入操作数栈

 3: istore_2       // 将栈顶值存入局部变量表索引 2

 4: iload_1        // 加载局部变量表索引 1 的值到栈顶

 5: iload_2        // 加载局部变量表索引 2 的值到栈顶

 6: iadd           // 栈顶两值相加，结果压入栈顶

 7: istore_3       // 将栈顶值存入局部变量表索引 3

 8: getstatic      // 获取静态字段

 9: ldc            // 将字符串 "Sum: " 加载到栈顶

10: invokevirtual  // 调用 println 方法

11: return         // 方法返回


程序计数器会依次指向 0, 1, 2 等字节码指令地址。

当 JVM 执行到 8: getstatic 时，程序计数器的值为 8。

## 线程切换中的作用
假设有两个线程执行任务，程序计数器帮助每个线程独立记录它的执行位置。

```java

public class ThreadExample {
    public static void main(String[] args) {
        Runnable task = () -> {
            for (int i = 0; i < 5; i++) {
                System.out.println(Thread.currentThread().getName() + " - Counter: " + i);
                try {
                    Thread.sleep(100); // 模拟线程切换
                } catch (InterruptedException e) {
                    Thread.currentThread().interrupt();
                }
            }
        };

        Thread thread1 = new Thread(task, "Thread-1");
        Thread thread2 = new Thread(task, "Thread-2");

        thread1.start();
        thread2.start();
    }
}
```

## 运行过程：

假设线程 Thread-1 执行到 System.out.println 时切换到 Thread-2。

Thread-1 的程序计数器记录了其执行的位置（例如，某个字节码地址）。

Thread-2 开始运行，并独立使用自己的程序计数器记录其执行位置。

当 Thread-1 恢复时，程序计数器帮助它继续从之前中断的位置执行。

# 总结

定义：程序计数器是 JVM 中一个线程私有的内存区域，记录当前线程正在执行的字节码指令地址。

主要作用：跟踪线程的执行位置，支持线程切换和控制程序流程。

特点：线程私有、大小固定、不可见。

状态：执行 Java 方法时记录字节码地址；执行本地方法时值为 Undefined。

核心作用：在多线程环境中确保线程独立执行和切换无误，是 JVM 实现线程安全的基础之一。

内容来自chatgpt的搜索和check
